image_modifier/__init__.py
image_modifier/add_frame.py
image_modifier/rotate_90.py
image_modifier/select_channel.py
image_modifier/slice_image.py
image_modifier-2.1.0.dist-info/LICENSE
image_modifier-2.1.0.dist-info/METADATA
image_modifier-2.1.0.dist-info/WHEEL
image_modifier-2.1.0.dist-info/RECORD
