Metadata-Version: 2.1
Name: image_modifier
Version: 2.1.0
Summary: Performs simple image modifications
License: MIT
Author: Karan Khubdikar, Celeste Zhao, He Ma, Chun Li
Requires-Python: >=3.9
Classifier: License :: OSI Approved :: MIT License
Classifier: Programming Language :: Python :: 3
Classifier: Programming Language :: Python :: 3.9
Classifier: Programming Language :: Python :: 3.10
Classifier: Programming Language :: Python :: 3.11
Classifier: Programming Language :: Python :: 3.12
Requires-Dist: matplotlib (>=3.8.2,<4.0.0)
Requires-Dist: numpy (>=1.26.3,<2.0.0)
Requires-Dist: pytest (>=7.4.4)
